nekrosis.py
nekrosis/__init__.py
nekrosis/__main__.py
nekrosis/core.py
nekrosis/support/__init__.py
nekrosis/support/base.py
nekrosis/support/error_wrapper.py
nekrosis/support/export.py
nekrosis/support/interpreter.py
nekrosis/support/linux.py
nekrosis/support/macos.py
nekrosis/support/nuclear.py
nekrosis/support/windows.py
nekrosis/support/linux_utilities/__init__.py
nekrosis/support/linux_utilities/persistence_methods.py
nekrosis/support/linux_utilities/systemd.py
nekrosis/support/macos_binaries/nm
nekrosis/support/macos_binaries/strings
nekrosis/support/macos_utilities/__init__.py
nekrosis/support/macos_utilities/electron.py
nekrosis/support/macos_utilities/electron_fuses.py
nekrosis/support/macos_utilities/launchd.py
nekrosis/support/macos_utilities/os_versioning.py
nekrosis/support/macos_utilities/persistence_methods.py
nekrosis/support/macos_utilities/root_volume.py
nekrosis/support/unix_utilities/__init__.py
nekrosis/support/unix_utilities/cronjob.py
nekrosis/support/unix_utilities/permissions.py
nekrosis/support/windows_utilities/__init__.py
nekrosis/support/windows_utilities/permissions.py
nekrosis/support/windows_utilities/persistence_methods.py
nekrosis/support/windows_utilities/regrun.py
nekrosis/support/windows_utilities/shortcut.py
nekrosis/support/windows_utilities/startup.py
nekrosis-1.0.0.dist-info/LICENSE.txt
nekrosis-1.0.0.dist-info/METADATA
nekrosis-1.0.0.dist-info/WHEEL
nekrosis-1.0.0.dist-info/entry_points.txt
nekrosis-1.0.0.dist-info/top_level.txt
nekrosis-1.0.0.dist-info/RECORD
