Metadata-Version: 2.1
Name: nekrosis
Version: 1.0.0
Summary: Multi-platform persistence toolkit for user-provided payloads.
Home-page: https://github.com/Nekrosis-ISS-Capstone/Nekrosis
Author: Ezra Fast, Mitchell Nicholson, Mykola Grymalyuk, Scott Banister and Ulysses Hill
Author-email: nekrosis-capstone@protonmail.com
License: 3-clause BSD License
Classifier: Programming Language :: Python :: 3
Classifier: License :: OSI Approved :: BSD License
Classifier: Operating System :: MacOS :: MacOS X
Classifier: Operating System :: Microsoft :: Windows
Classifier: Operating System :: POSIX :: Linux
Classifier: Development Status :: 5 - Production/Stable
Requires-Python: >=3.6
License-File: LICENSE.txt
Requires-Dist: requests >=2.25.1
Requires-Dist: py-sip-xnu >=1.0.4 ; sys_platform == "darwin"
Requires-Dist: dbus-python >=1.0.0 ; sys_platform == "linux"
Requires-Dist: pywin32 >=306 ; sys_platform == "win32"
